add_labels_to_fcs/__init__.py
add_labels_to_fcs/add_labels.py
add_labels_to_fcs/handy.py
add_labels_to_fcs/hello.py
add_labels_to_fcs-0.4.0.dist-info/LICENSE
add_labels_to_fcs-0.4.0.dist-info/METADATA
add_labels_to_fcs-0.4.0.dist-info/WHEEL
add_labels_to_fcs-0.4.0.dist-info/entry_points.txt
add_labels_to_fcs-0.4.0.dist-info/top_level.txt
add_labels_to_fcs-0.4.0.dist-info/RECORD
