Metadata-Version: 2.1
Name: add_labels_to_fcs
Version: 0.4.0
Summary: Package for adding columns of data to FCS files as additional channels
Home-page: https://github.com/SimonsonLab/add-labels-to-fcs
Author: Paul D. Simonson
License-File: LICENSE
Requires-Dist: pandas>=2.2
Requires-Dist: openpyxl>=3.1
Requires-Dist: numpy>=1.26
Requires-Dist: flowkit>=1.1
